pyterminate/__init__.py
pyterminate/py.typed
pyterminate-0.0.8.dist-info/LICENSE
pyterminate-0.0.8.dist-info/METADATA
pyterminate-0.0.8.dist-info/WHEEL
pyterminate-0.0.8.dist-info/top_level.txt
pyterminate-0.0.8.dist-info/RECORD
