Metadata-Version: 2.1
Name: pyterminate
Version: 0.0.8
Summary: Exit programs gracefully.
Home-page: https://github.com/jeremyephron/pyterminate
Author: Jeremy Ephron
Author-email: jeremye@cs.stanford.edu
License: UNKNOWN
Platform: UNKNOWN
Classifier: Development Status :: 3 - Alpha
Classifier: Programming Language :: Python
Classifier: Programming Language :: Python :: 3
Classifier: Programming Language :: Python :: 3.8
Classifier: Programming Language :: Python :: 3.9
Classifier: Programming Language :: Python :: 3.10
Classifier: Programming Language :: Python :: 3.11
Classifier: License :: OSI Approved :: MIT License
Classifier: Operating System :: MacOS
Classifier: Operating System :: Unix
License-File: LICENSE
